login_canary/settings.py
login_canary/notify.py
login_canary/apps.py
login_canary/__init__.py
login_canary/templates/login_canary/logged_in_body.txt
login_canary/templates/login_canary/login_failed_subject.txt
login_canary/templates/login_canary/login_failed_body.txt
login_canary/templates/login_canary/logged_in_subject.txt
login_canary/migrations/__init__.py
login_canary/locale/en/LC_MESSAGES/django.po
login_canary/locale/en/LC_MESSAGES/django.mo
login_canary/locale/de/LC_MESSAGES/django.po
login_canary/locale/de/LC_MESSAGES/django.mo
django_login_canary-0.1.0.dist-info/RECORD
django_login_canary-0.1.0.dist-info/METADATA
django_login_canary-0.1.0.dist-info/DESCRIPTION.rst
django_login_canary-0.1.0.dist-info/top_level.txt
django_login_canary-0.1.0.dist-info/metadata.json
django_login_canary-0.1.0.dist-info/WHEEL
django_login_canary-0.1.0.dist-info/LICENSE.txt
