Metadata-Version: 2.0
Name: django-login-canary
Version: 0.1.0
Summary: django-login-canary is a reusable Django application to notify users upon successful and failed logins.
Home-page: http://github.com/MarkusH/django-login-canary
Author: Markus Holtermann
Author-email: info@markusholtermann.eu
License: MIT
Platform: UNKNOWN
Classifier: Development Status :: 4 - Beta
Classifier: Environment :: Web Environment
Classifier: Intended Audience :: Developers
Classifier: License :: OSI Approved :: MIT License
Classifier: Operating System :: OS Independent
Classifier: Programming Language :: Python
Classifier: Programming Language :: Python :: 2
Classifier: Programming Language :: Python :: 2.7
Classifier: Programming Language :: Python :: 3
Classifier: Programming Language :: Python :: 3.2
Classifier: Programming Language :: Python :: 3.3
Classifier: Programming Language :: Python :: 3.4
Classifier: Framework :: Django
Classifier: Framework :: Django :: 1.8
Requires-Dist: Django (>=1.8)
